{"cameraMode":{"drawMode":0,"name":"Shaded","section":"Shading Mode"},"sceneLighting":true,"audioPlay":false,"sceneViewState":{"showFog":true,"showMaterialUpdate":false,"showSkybox":true,"showFlares":true,"showImageEffects":true,"showParticleSystems":true},"in2DMode":false,"pivot":{"x":-3.644108772277832,"y":4.586853981018066,"z":-4.21913480758667},"rotation":{"x":-0.22757253050804139,"y":-0.4218514859676361,"z":0.1096021756529808,"w":-0.8709728717803955},"size":5.107395172119141,"orthographic":false}